mdelta/Pvalue.py
mdelta/ReadFile.py
mdelta/__init__.py
mdelta/auxi.py
mdelta/mDELTA.py
mdelta/mymath.py
mdelta/mytest.py
mdelta-1.0.38.dist-info/LICENSE
mdelta-1.0.38.dist-info/METADATA
mdelta-1.0.38.dist-info/WHEEL
mdelta-1.0.38.dist-info/top_level.txt
mdelta-1.0.38.dist-info/RECORD
